DjangoZhongwenWendang1820170215/README.md
DjangoZhongwenWendang1820170215/__init__.py
DjangoZhongwenWendang1820170215/__main__.py
DjangoZhongwenWendang1820170215/file.epub
DjangoZhongwenWendang1820170215/index.html
DjangoZhongwenWendang1820170215/css/__init__.py
DjangoZhongwenWendang1820170215/css/annotations.css
DjangoZhongwenWendang1820170215/css/main.css
DjangoZhongwenWendang1820170215/css/normalize.css
DjangoZhongwenWendang1820170215/css/popup.css
DjangoZhongwenWendang1820170215/font/__init__.py
DjangoZhongwenWendang1820170215/font/fontello.eot
DjangoZhongwenWendang1820170215/font/fontello.svg
DjangoZhongwenWendang1820170215/font/fontello.ttf
DjangoZhongwenWendang1820170215/font/fontello.woff
DjangoZhongwenWendang1820170215/img/__init__.py
DjangoZhongwenWendang1820170215/img/annotator-glyph-sprite.png
DjangoZhongwenWendang1820170215/img/annotator-icon-sprite.png
DjangoZhongwenWendang1820170215/img/apple-touch-icon.png
DjangoZhongwenWendang1820170215/img/cancelfullscreen.png
DjangoZhongwenWendang1820170215/img/close.png
DjangoZhongwenWendang1820170215/img/fullscreen.png
DjangoZhongwenWendang1820170215/img/loader.gif
DjangoZhongwenWendang1820170215/img/menu-icon.png
DjangoZhongwenWendang1820170215/img/save.png
DjangoZhongwenWendang1820170215/img/saved.png
DjangoZhongwenWendang1820170215/img/settings-s.png
DjangoZhongwenWendang1820170215/img/settings.png
DjangoZhongwenWendang1820170215/img/star.png
DjangoZhongwenWendang1820170215/js/__init__.py
DjangoZhongwenWendang1820170215/js/epub.js
DjangoZhongwenWendang1820170215/js/epub.min.js
DjangoZhongwenWendang1820170215/js/epub.min.map
DjangoZhongwenWendang1820170215/js/hooks.min.js
DjangoZhongwenWendang1820170215/js/hooks.min.map
DjangoZhongwenWendang1820170215/js/reader.js
DjangoZhongwenWendang1820170215/js/reader.js.map
DjangoZhongwenWendang1820170215/js/reader.min.js
DjangoZhongwenWendang1820170215/js/reader.min.map
DjangoZhongwenWendang1820170215/js/hooks/__init__.py
django_zhongwen_wendang_1_8_20170215-2024.3.2.0.dist-info/METADATA
django_zhongwen_wendang_1_8_20170215-2024.3.2.0.dist-info/WHEEL
django_zhongwen_wendang_1_8_20170215-2024.3.2.0.dist-info/entry_points.txt
django_zhongwen_wendang_1_8_20170215-2024.3.2.0.dist-info/top_level.txt
django_zhongwen_wendang_1_8_20170215-2024.3.2.0.dist-info/RECORD
